markslack/__init__.py
markslack/test_lib.py
markslack-0.0.7.dist-info/METADATA
markslack-0.0.7.dist-info/WHEEL
markslack-0.0.7.dist-info/top_level.txt
markslack-0.0.7.dist-info/RECORD
