Metadata-Version: 2.1
Name: markslack
Version: 0.0.7
Summary: A Slack message format to Markdown converter
Home-page: https://github.com/The-Politico/markslack
Author: Jon McClure
Author-email: jon.r.mcclure@gmail.com
License: MIT
Keywords: slack markdown
Platform: UNKNOWN
Classifier: Development Status :: 3 - Alpha
Classifier: Intended Audience :: Developers
Classifier: Intended Audience :: Information Technology
Classifier: License :: OSI Approved :: MIT License
Classifier: Operating System :: OS Independent
Classifier: Programming Language :: Python :: 2
Classifier: Programming Language :: Python :: 2.7
Classifier: Programming Language :: Python :: 3
Classifier: Programming Language :: Python :: 3.5
Classifier: Topic :: Internet :: WWW/HTTP
Requires-Dist: emoji
Provides-Extra: test
Requires-Dist: pytest ; extra == 'test'
